pyhesive/__about__.py
pyhesive/__init__.py
pyhesive/_cell_set.py
pyhesive/_mesh.py
pyhesive/_partition_interface.py
pyhesive/_utils.py
pyhesive-1.2.data/scripts/pyhesive-insert
pyhesive-1.2.dist-info/LICENSE
pyhesive-1.2.dist-info/METADATA
pyhesive-1.2.dist-info/WHEEL
pyhesive-1.2.dist-info/top_level.txt
pyhesive-1.2.dist-info/RECORD
