Metadata-Version: 2.1
Name: pyhesive
Version: 1.2
Summary: Insert cohesive elements into any mesh
Home-page: https://gitlab.com/Jfaibussowitsch/pyhesive
Author: Jacob Faibussowitsch
Author-email: jacob.fai@gmail.com
Keywords: mesh,meshing,scientific,engineering,library,fem,finite elements,fracture,fracture mechanics,cohesive elements,cohesive zone model
Classifier: Development Status :: 5 - Production/Stable
Classifier: Programming Language :: Python
Classifier: Programming Language :: Python :: 3
Classifier: Programming Language :: Python :: 3 :: Only
Classifier: Programming Language :: Python :: 3.2
Classifier: License :: OSI Approved :: MIT License
Classifier: Operating System :: OS Independent
Classifier: Environment :: Console
Classifier: Intended Audience :: Science/Research
Classifier: Topic :: Multimedia :: Graphics :: 3D Modeling
Classifier: Topic :: Scientific/Engineering
Classifier: Topic :: Scientific/Engineering :: Mathematics
Classifier: Topic :: Scientific/Engineering :: Visualization
Classifier: Topic :: Software Development :: Libraries
Classifier: Topic :: Utilities
Requires-Python: >=3.2
License-File: LICENSE
Requires-Dist: numpy
Requires-Dist: scipy
Requires-Dist: meshio
Requires-Dist: pymetis
Provides-Extra: test
Requires-Dist: pytest ; extra == 'test'
Requires-Dist: pytest-xdist ; extra == 'test'
Requires-Dist: pytest-cov ; extra == 'test'
Requires-Dist: pytest-subtests ; extra == 'test'
Requires-Dist: snakeviz ; extra == 'test'
Requires-Dist: vermin ; extra == 'test'
